{
	"$schema": "sublime://packagecontrol.io/schemas/repository",
	"schema_version": "3.0.0",
	"packages": [
		{
			"name": "GoToTest-guille",
			"details": "https://github.com/guille/GoToTest",
			"releases": [
				{
					"sublime_text": ">=4000",
					"tags": true
				}
			]
		},
		{
			"name": "Elixir-guille",
			"details": "https://github.com/guille/elixir-sublime-syntax",
			"releases": [
				{
					"sublime_text": ">=4000",
					"tags": true
				}
			]
		},
		{
			"name": "Helm-guille",
			"details": "https://github.com/guille/sublime-helm",
			"releases": [
				{
					"sublime_text": ">=4000",
					"tags": true
				}
			]
		},
		{
			"name": "Dart-guille",
			"details": "https://github.com/guille/sublime-dart",
			"releases": [
				{
					"sublime_text": ">=4000",
					"tags": true
				}
			]
		}
	]
}
